rconf/__init__.py
rconf/_error.py
rconf/_load.py
rconf/_value.py
rconf/py.typed
rconf/decode/__init__.py
rconf/decode/_director.py
rconf/decode/_error.py
rconf/decode/_handler.py
rconf/decode/_ini.py
rconf/decode/_json.py
rconf/decode/_toml.py
rconf/patch/__init__.py
rconf/patch/_error.py
rconf/patch/_object.py
rconf/patch/_operation.py
rconf/patch/_patch.py
rconf/pointer/__init__.py
rconf/pointer/_error.py
rconf/pointer/_json.py
rconf/pointer/_pointer.py
rconf/pointer/_toml.py
rconf/scripts/__init__.py
rconf/scripts/argparse.py
rconf/scripts/config.py
rconf/scripts/dump.py
rconf/scripts/rconf.py
rconf/scripts/rconf.toml
rconf-0.0.5.dist-info/LICENSE
rconf-0.0.5.dist-info/METADATA
rconf-0.0.5.dist-info/WHEEL
rconf-0.0.5.dist-info/entry_points.txt
rconf-0.0.5.dist-info/top_level.txt
rconf-0.0.5.dist-info/RECORD
