Metadata-Version: 2.1
Name: rconf
Version: 0.0.5
Summary: Extensible Python package to resolve references and apply patches in JSON and TOML configurations
Author-email: Filip Thyssen <filip.thyssen@gmail.com>
License: MIT License
Project-URL: Documentation, http://fthyssen.github.io/rconf
Project-URL: Homepage, https://github.com/fthyssen/rconf
Project-URL: Repository, https://github.com/fthyssen/rconf
Keywords: toml,json,reference,pointer,patch,configuration
Classifier: Programming Language :: Python :: 3
Classifier: Operating System :: OS Independent
Requires-Python: >=3.7
License-File: LICENSE
Requires-Dist: tomli ~=2.0 ; python_version < "3.11"
Requires-Dist: typing-extensions >=4.0.0 ; python_version < "3.11"
Requires-Dist: importlib-metadata >=1.4.0 ; python_version < "3.8"
Provides-Extra: sh
Requires-Dist: argcomplete >=2.0.0 ; extra == 'sh'
